AUTHORS.rst
CHANGELOG.rst
LICENSE
MANIFEST.in
README.rst
setup.py
django_richcomments.egg-info/PKG-INFO
django_richcomments.egg-info/SOURCES.txt
django_richcomments.egg-info/dependency_links.txt
django_richcomments.egg-info/not-zip-safe
django_richcomments.egg-info/top_level.txt
richcomments/__init__.py
richcomments/models.py
richcomments/tests.py
richcomments/urls.py
richcomments/views.py
richcomments/static/richcomments/includes/jquery.form.js
richcomments/static/richcomments/includes/jquery.min.js
richcomments/templates/richcomments/form_js.html
richcomments/templates/richcomments/list_wrapper.html
richcomments/templates/richcomments/templatetags/richcomments_static.html
richcomments/templatetags/__init__.py
richcomments/templatetags/richcomments.py