Metadata-Version: 1.0
Name: django-richcomments
Version: 0.0.2
Summary: Django app extending the builtin comments framework for AJAX style commenting.
Home-page: http://github.com/praekelt/django-richcomments
Author: Praekelt Foundation
Author-email: dev@praekelt.com
License: BSD
Platform: UNKNOWN
Classifier: Programming Language :: Python
Classifier: License :: OSI Approved :: BSD License
Classifier: Development Status :: 4 - Beta
Classifier: Operating System :: OS Independent
Classifier: Framework :: Django
Classifier: Intended Audience :: Developers
Classifier: Topic :: Internet :: WWW/HTTP :: Dynamic Content
